README.md
setup.py
prepare_wda/__init__.py
prepare_wda/wda.sh
prewda.egg-info/PKG-INFO
prewda.egg-info/SOURCES.txt
prewda.egg-info/dependency_links.txt
prewda.egg-info/requires.txt
prewda.egg-info/top_level.txt