Metadata-Version: 1.2
Name: prewda
Version: 0.0.3
Summary: a python wrapper for WebDriverAgent prepare
Home-page: https://github.com/ssfanli/prepare-wda.git
Author: ssfanli
Author-email: freedomlidi@163.com
License: MIT
Platform: UNKNOWN
Requires-Python: >=3.6
